{"nianticlabs.com": {"observatory_result": {"algorithm_version": 2, "end_time": "Wed, 16 Feb 2022 05:57:45 GMT", "grade": "D", "hidden": true, "likelihood_indicator": "MEDIUM", "response_headers": {"Cache-Control": "no-cache", "Content-Encoding": "gzip", "Content-Type": "text/html", "Date": "Wed, 16 Feb 2022 05:57:44 GMT", "ETag": "\"e4ba23e8e9a879c98ff93bfd91562de9658bbc2f\"", "Server": "Google Frontend", "Transfer-Encoding": "chunked", "X-Cloud-Trace-Context": "91c31ed9818a9dd83c2549df2932e164", "X-Frame-Options": "deny"}, "scan_id": 24557676, "score": 35, "start_time": "Wed, 16 Feb 2022 05:57:42 GMT", "state": "FINISHED", "status_code": 200, "tests_failed": 5, "tests_passed": 7, "tests_quantity": 12}, "trancos_rank": 6993}}